{
  "resourceType": "ValueSet",
  "status": "active",
  "name": "UnitsOfLengthVS",
  "id": "UnitsOfLengthVS",
  "title": "Units of Length Value Set",
  "description": "Units of measure for length or distance on a human scale.",
  "version": "0.9.5",
  "url": "http://hl7.org/fhir/us/mcode/ValueSet/UnitsOfLengthVS",
  "compose": {
    "include": [
      {
        "system": "http://unitsofmeasure.org",
        "concept": [
          {
            "code": "mm",
            "display": "Millimeter"
          },
          {
            "code": "cm",
            "display": "Centimeter"
          },
          {
            "code": "m",
            "display": "Meter"
          },
          {
            "code": "ft-us",
            "display": "Foot"
          },
          {
            "code": "in-us",
            "display": "Inch"
          }
        ]
      }
    ]
  }
}